directnet/__init__.py
directnet/common.py
directnet/dn_client.py
directnet/ks_client.py
directnet/ks_net_client.py
directnet/tests.py
directnet-2.1.dist-info/METADATA
directnet-2.1.dist-info/RECORD
directnet-2.1.dist-info/WHEEL
directnet-2.1.dist-info/top_level.txt
