Metadata-Version: 2.1
Name: directnet
Version: 2.1
Summary: DirectNET communication library
Home-page: https://github.com/cuchac/directnet
Author: Cuchac
Author-email: cuchac@email.cz
License: LGPL v2
Platform: UNKNOWN
Requires-Dist: pyserial
Requires-Dist: six
